CHANGELOG.rst
CONTRIBUTING.md
LICENSE.txt
MANIFEST.in
README.md
requirements.txt
setup.cfg
setup.py
mssqlcli/__init__.py
mssqlcli/cli.py
mssqlcli/config.py
mssqlcli/formats.py
mssqlcli/test_cli.py
mssqlcli/test_config.py
mssqlcli/test_formats.py
mssqlcli.egg-info/PKG-INFO
mssqlcli.egg-info/SOURCES.txt
mssqlcli.egg-info/dependency_links.txt
mssqlcli.egg-info/entry_points.txt
mssqlcli.egg-info/requires.txt
mssqlcli.egg-info/top_level.txt
mssqlcli/drivers/__init__.py
mssqlcli/drivers/mssql.py