Metadata-Version: 1.1
Name: mssqlcli
Version: 1.0.3
Summary: Python CLI for Microsoft SQL.
Home-page: https://github.com/rtrox/mssqlcli
Author: Russell Troxel
Author-email: russelltroxel@gmail.com
License: GPLv3
Keywords: microsoft,sql,mssql
Platform: UNKNOWN
Classifier: Development Status :: 4 - Beta
Classifier: Intended Audience :: System Administrators
Classifier: Topic :: Database :: Front-Ends
Classifier: License :: OSI Approved :: GNU General Public License v3 (GPLv3)
Classifier: Operating System :: MacOS :: MacOS X
Classifier: Operating System :: Unix
Classifier: Operating System :: POSIX
Classifier: Programming Language :: Python :: 2
Classifier: Programming Language :: Python :: 2.7
Classifier: Programming Language :: Python :: 3.5
